blaze/__init__.py
blaze/config.py
blaze/find_reads.py
blaze/helper.py
blaze/main.py
blaze/parser.py
blaze/polyT_adaptor_finder.py
blaze/polyT_trimmer.py
blaze/read_assignment.py
blaze/10X_bc/3M-3pgex-may-2023.zip
blaze/10X_bc/3M-5pgex-jan-2023.zip
blaze/10X_bc/3M-february-2018.zip
blaze/10X_bc/737K-august-2016.txt
blaze/10X_bc/visium-v2.txt
blaze2-2.5.1.dist-info/LICENSE
blaze2-2.5.1.dist-info/METADATA
blaze2-2.5.1.dist-info/WHEEL
blaze2-2.5.1.dist-info/entry_points.txt
blaze2-2.5.1.dist-info/top_level.txt
blaze2-2.5.1.dist-info/RECORD
