Metadata-Version: 2.1
Name: blaze2
Version: 2.5.1
Summary: Barcode identification from Long reads for AnalyZing single cell gene Expression
Author-email: Yupei You <youyupei@gmail.com>
License: GNU General Public License v3 (GPLv3)
Project-URL: Source, https://github.com/shimlab/BLAZE
Classifier: Programming Language :: Python :: 3
Classifier: License :: OSI Approved :: GNU General Public License v3 (GPLv3)
Classifier: Operating System :: OS Independent
Requires-Python: >=3.7
License-File: LICENSE
Requires-Dist: fast-edit-distance==1.2.2
Requires-Dist: matplotlib
Requires-Dist: tqdm
Requires-Dist: numpy
Requires-Dist: pandas
